{"cameraMode":{"drawMode":0,"name":"Shaded","section":"Shading Mode"},"sceneLighting":true,"audioPlay":false,"sceneViewState":{"showFog":true,"showMaterialUpdate":false,"showSkybox":true,"showFlares":true,"showImageEffects":true,"showParticleSystems":true},"in2DMode":false,"pivot":{"x":1.191734790802002,"y":11.60754108428955,"z":-3.8085250854492189},"rotation":{"x":0.0002532389771658927,"y":0.999728798866272,"z":0.013187498785555363,"w":-0.019196292385458947},"size":14.2799072265625,"orthographic":false}